data_modori/__init__.py
data_modori/analysis/__init__.py
data_modori/analysis/column_wise_analysis.py
data_modori/analysis/diversity_analysis.py
data_modori/analysis/overall_analysis.py
data_modori/config/__init__.py
data_modori/config/config.py
data_modori/core/__init__.py
data_modori/core/analyser.py
data_modori/core/data.py
data_modori/core/executor.py
data_modori/core/exporter.py
data_modori/core/ray_executor.py
data_modori/core/tracer.py
data_modori/format/__init__.py
data_modori/format/csv_formatter.py
data_modori/format/formatter.py
data_modori/format/json_formatter.py
data_modori/format/load.py
data_modori/format/mixture_formatter.py
data_modori/format/parquet_formatter.py
data_modori/format/text_formatter.py
data_modori/format/tsv_formatter.py
data_modori/ops/__init__.py
data_modori/ops/base_op.py
data_modori/ops/load.py
data_modori/ops/op_fusion.py
data_modori/ops/common/__init__.py
data_modori/ops/common/aws_s3_downloader.py
data_modori/ops/common/helper_func.py
data_modori/ops/common/special_characters.py
data_modori/ops/deduplicator/__init__.py
data_modori/ops/deduplicator/document_deduplicator.py
data_modori/ops/deduplicator/document_minhash_deduplicator.py
data_modori/ops/deduplicator/document_simhash_deduplicator.py
data_modori/ops/filter/__init__.py
data_modori/ops/filter/alphanumeric_filter.py
data_modori/ops/filter/average_line_length_filter.py
data_modori/ops/filter/character_repetition_filter.py
data_modori/ops/filter/flagged_words_filter.py
data_modori/ops/filter/language_id_score_filter.py
data_modori/ops/filter/maximum_line_length_filter.py
data_modori/ops/filter/perplexity_filter.py
data_modori/ops/filter/special_characters_filter.py
data_modori/ops/filter/specified_field_filter.py
data_modori/ops/filter/specified_numeric_field_filter.py
data_modori/ops/filter/stopwords_filter.py
data_modori/ops/filter/suffix_filter.py
data_modori/ops/filter/text_length_filter.py
data_modori/ops/filter/token_num_filter.py
data_modori-0.1.5.dist-info/LICENSE
data_modori-0.1.5.dist-info/METADATA
data_modori-0.1.5.dist-info/WHEEL
data_modori-0.1.5.dist-info/entry_points.txt
data_modori-0.1.5.dist-info/top_level.txt
data_modori-0.1.5.dist-info/RECORD
