Metadata-Version: 2.1
Name: data-modori
Version: 0.1.5
Summary: LMOps Tool for Korean
Home-page: https://github.com/teamreboott/data-modori
Author: TeamAR of Teamreboott
License: Apache License 2.0
Classifier: License :: OSI Approved :: Apache Software License
Classifier: Programming Language :: Python :: 3
Classifier: Operating System :: OS Independent
License-File: LICENSE
Requires-Dist: fsspec ==2023.3.0
Requires-Dist: pyarrow <=12.0.0
Requires-Dist: pandas ==2.0.0
Requires-Dist: datasets ==2.11.0
Requires-Dist: loguru
Requires-Dist: tabulate
Requires-Dist: tqdm
Requires-Dist: jsonargparse[signatures]
Requires-Dist: matplotlib
Requires-Dist: emoji ==2.2.0
Requires-Dist: regex
Requires-Dist: requests
Requires-Dist: wget
Requires-Dist: zstandard
Requires-Dist: lz4
Requires-Dist: pdfplumber
Requires-Dist: plotly
Requires-Dist: python-docx
Requires-Dist: streamlit
Requires-Dist: spacy ==3.5.0
Requires-Dist: multiprocess ==0.70.12
Requires-Dist: dill ==0.3.4
Requires-Dist: scipy
Requires-Dist: boto3 <=1.15.18
Requires-Dist: simhash-py
Requires-Dist: gluonnlp <=0.10.0,>=0.6.0
Requires-Dist: mxnet <=1.7.0.post2,>=1.4.0
Requires-Dist: onnxruntime <=1.8.0,==1.8.0
Requires-Dist: numpy ==1.23.1
Requires-Dist: selectolax
Requires-Dist: ftfy
Requires-Dist: nlpaug
Requires-Dist: ray
Requires-Dist: fasttext ==0.9.2
Requires-Dist: sentencepiece <=0.1.96,>=0.1.6
Requires-Dist: pypi-kenlm ==0.1.20220713
Requires-Dist: transformers
Requires-Dist: fasttext-wheel
Requires-Dist: nlpcda
Requires-Dist: nltk
Requires-Dist: opencc ==1.1.6
Requires-Dist: imagededup
Requires-Dist: torch <=1.10.1,>=1.7.0
Requires-Dist: dlib
Requires-Dist: spacy-pkuseg ==0.0.32
Requires-Dist: kenlm
Requires-Dist: omegaconf
Provides-Extra: all
Requires-Dist: fsspec ==2023.3.0 ; extra == 'all'
Requires-Dist: pyarrow <=12.0.0 ; extra == 'all'
Requires-Dist: pandas ==2.0.0 ; extra == 'all'
Requires-Dist: datasets ==2.11.0 ; extra == 'all'
Requires-Dist: loguru ; extra == 'all'
Requires-Dist: tabulate ; extra == 'all'
Requires-Dist: tqdm ; extra == 'all'
Requires-Dist: jsonargparse[signatures] ; extra == 'all'
Requires-Dist: matplotlib ; extra == 'all'
Requires-Dist: emoji ==2.2.0 ; extra == 'all'
Requires-Dist: regex ; extra == 'all'
Requires-Dist: requests ; extra == 'all'
Requires-Dist: wget ; extra == 'all'
Requires-Dist: zstandard ; extra == 'all'
Requires-Dist: lz4 ; extra == 'all'
Requires-Dist: pdfplumber ; extra == 'all'
Requires-Dist: plotly ; extra == 'all'
Requires-Dist: python-docx ; extra == 'all'
Requires-Dist: streamlit ; extra == 'all'
Requires-Dist: spacy ==3.5.0 ; extra == 'all'
Requires-Dist: multiprocess ==0.70.12 ; extra == 'all'
Requires-Dist: dill ==0.3.4 ; extra == 'all'
Requires-Dist: scipy ; extra == 'all'
Requires-Dist: boto3 <=1.15.18 ; extra == 'all'
Requires-Dist: simhash-py ; extra == 'all'
Requires-Dist: gluonnlp <=0.10.0,>=0.6.0 ; extra == 'all'
Requires-Dist: mxnet <=1.7.0.post2,>=1.4.0 ; extra == 'all'
Requires-Dist: onnxruntime <=1.8.0,==1.8.0 ; extra == 'all'
Requires-Dist: numpy ==1.23.1 ; extra == 'all'
Requires-Dist: selectolax ; extra == 'all'
Requires-Dist: ftfy ; extra == 'all'
Requires-Dist: nlpaug ; extra == 'all'
Requires-Dist: ray ; extra == 'all'
Requires-Dist: fasttext ==0.9.2 ; extra == 'all'
Requires-Dist: sentencepiece <=0.1.96,>=0.1.6 ; extra == 'all'
Requires-Dist: pypi-kenlm ==0.1.20220713 ; extra == 'all'
Requires-Dist: transformers ; extra == 'all'
Requires-Dist: fasttext-wheel ; extra == 'all'
Requires-Dist: nlpcda ; extra == 'all'
Requires-Dist: nltk ; extra == 'all'
Requires-Dist: opencc ==1.1.6 ; extra == 'all'
Requires-Dist: imagededup ; extra == 'all'
Requires-Dist: torch <=1.10.1,>=1.7.0 ; extra == 'all'
Requires-Dist: dlib ; extra == 'all'
Requires-Dist: spacy-pkuseg ==0.0.32 ; extra == 'all'
Requires-Dist: kenlm ; extra == 'all'
Requires-Dist: omegaconf ; extra == 'all'
Requires-Dist: pre-commit ; extra == 'all'
Requires-Dist: sphinx ; extra == 'all'
Requires-Dist: sphinx-autobuild ; extra == 'all'
Requires-Dist: sphinx-rtd-theme ; extra == 'all'
Requires-Dist: recommonmark ; extra == 'all'
Requires-Dist: fire ; extra == 'all'
Requires-Dist: jsonlines ; extra == 'all'
Requires-Dist: pyspark ; extra == 'all'
Provides-Extra: dev
Requires-Dist: pre-commit ; extra == 'dev'
Requires-Dist: sphinx ; extra == 'dev'
Requires-Dist: sphinx-autobuild ; extra == 'dev'
Requires-Dist: sphinx-rtd-theme ; extra == 'dev'
Requires-Dist: recommonmark ; extra == 'dev'
Provides-Extra: mini
Requires-Dist: fsspec ==2023.3.0 ; extra == 'mini'
Requires-Dist: pyarrow <=12.0.0 ; extra == 'mini'
Requires-Dist: pandas ==2.0.0 ; extra == 'mini'
Requires-Dist: datasets ==2.11.0 ; extra == 'mini'
Requires-Dist: loguru ; extra == 'mini'
Requires-Dist: tabulate ; extra == 'mini'
Requires-Dist: tqdm ; extra == 'mini'
Requires-Dist: jsonargparse[signatures] ; extra == 'mini'
Requires-Dist: matplotlib ; extra == 'mini'
Requires-Dist: emoji ==2.2.0 ; extra == 'mini'
Requires-Dist: regex ; extra == 'mini'
Requires-Dist: requests ; extra == 'mini'
Requires-Dist: wget ; extra == 'mini'
Requires-Dist: zstandard ; extra == 'mini'
Requires-Dist: lz4 ; extra == 'mini'
Requires-Dist: pdfplumber ; extra == 'mini'
Requires-Dist: plotly ; extra == 'mini'
Requires-Dist: python-docx ; extra == 'mini'
Requires-Dist: streamlit ; extra == 'mini'
Requires-Dist: spacy ==3.5.0 ; extra == 'mini'
Requires-Dist: multiprocess ==0.70.12 ; extra == 'mini'
Requires-Dist: dill ==0.3.4 ; extra == 'mini'
Requires-Dist: scipy ; extra == 'mini'
Requires-Dist: boto3 <=1.15.18 ; extra == 'mini'
Requires-Dist: simhash-py ; extra == 'mini'
Requires-Dist: gluonnlp <=0.10.0,>=0.6.0 ; extra == 'mini'
Requires-Dist: mxnet <=1.7.0.post2,>=1.4.0 ; extra == 'mini'
Requires-Dist: onnxruntime <=1.8.0,==1.8.0 ; extra == 'mini'
Requires-Dist: numpy ==1.23.1 ; extra == 'mini'
Requires-Dist: selectolax ; extra == 'mini'
Requires-Dist: ftfy ; extra == 'mini'
Requires-Dist: nlpaug ; extra == 'mini'
Requires-Dist: ray ; extra == 'mini'
Requires-Dist: fasttext ==0.9.2 ; extra == 'mini'
Requires-Dist: sentencepiece <=0.1.96,>=0.1.6 ; extra == 'mini'
Requires-Dist: pypi-kenlm ==0.1.20220713 ; extra == 'mini'
Requires-Dist: transformers ; extra == 'mini'
Requires-Dist: fasttext-wheel ; extra == 'mini'
Requires-Dist: nlpcda ; extra == 'mini'
Requires-Dist: nltk ; extra == 'mini'
Requires-Dist: opencc ==1.1.6 ; extra == 'mini'
Requires-Dist: imagededup ; extra == 'mini'
Requires-Dist: torch <=1.10.1,>=1.7.0 ; extra == 'mini'
Requires-Dist: dlib ; extra == 'mini'
Requires-Dist: spacy-pkuseg ==0.0.32 ; extra == 'mini'
Requires-Dist: kenlm ; extra == 'mini'
Requires-Dist: omegaconf ; extra == 'mini'
Provides-Extra: tools
Requires-Dist: fire ; extra == 'tools'
Requires-Dist: jsonlines ; extra == 'tools'
Requires-Dist: pyspark ; extra == 'tools'
Requires-Dist: wget ; extra == 'tools'
